dephell_argparse-0.1.3.dist-info/dependency_links.txt
dephell_argparse-0.1.3.dist-info/entry_points.txt
dephell_argparse-0.1.3.dist-info/METADATA
dephell_argparse-0.1.3.dist-info/top_level.txt
dephell_argparse-0.1.3.dist-info/WHEEL
dephell_argparse/_cached_property.py
dephell_argparse/_command.py
dephell_argparse/_handler.py
dephell_argparse/_colors.py
dephell_argparse/__init__.py
dephell_argparse/_parser.py
dephell_argparse-0.1.3.dist-info/LICENSE
dephell_argparse-0.1.3.dist-info/RECORD