Metadata-Version: 2.1
Name: dephell-argparse
Version: 0.1.3
Summary: Argparse on steroids: groups, commands, colors.
Project-URL: Homepage, https://github.com/dephell/dephell_argparse
Author: Gram (@orsinium)
Author-email: master_fess@mail.ru
Requires-Python: >=3.5
Classifier: Development Status :: 5 - Production/Stable
Classifier: Environment :: Console
Classifier: Intended Audience :: Developers
Classifier: License :: OSI Approved :: MIT License
Classifier: Programming Language :: Python :: 3.5
Classifier: Programming Language :: Python :: 3.6
Classifier: Programming Language :: Python :: 3.7
Classifier: Programming Language :: Python :: 3
Classifier: Programming Language :: Python
Classifier: Topic :: Software Development :: Libraries :: Python Modules
Classifier: Topic :: Software Development :: Quality Assurance
